d2apy/__init__.py
d2apy/__main__.py
d2apy/dhis2api.py
d2apy-1.0.0.dist-info/DESCRIPTION.rst
d2apy-1.0.0.dist-info/METADATA
d2apy-1.0.0.dist-info/RECORD
d2apy-1.0.0.dist-info/WHEEL
d2apy-1.0.0.dist-info/metadata.json
d2apy-1.0.0.dist-info/top_level.txt
